LICENSE.txt
MANIFEST.in
setup.py
experimental/deconvolution.py
experimental/diffraction.py
experimental/ellipses.py
experimental/flat.py
experimental/fwhm.py
experimental/noise_reduction.py
experimental/sky-magnitude.py
experimental/snr.py
experimental/sr.py
profiling/performance.py
src/c_modules/clusterization/module.cc
src/c_modules/clusterization/lib/run_valgrind_tests.sh
src/c_modules/clusterization/lib/include/clusters.hpp
src/c_modules/clusterization/lib/src/clusters.cc
src/c_modules/clusterization/lib/tests/clusters_test.cc
src/c_modules/fine_movement/libimagedeform/run_valgrind_tests.sh
src/c_modules/fine_movement/libimagedeform/include/image_deform.h
src/c_modules/fine_movement/libimagedeform/include/image_deform_gc.h
src/c_modules/fine_movement/libimagedeform/include/image_deform_lc.h
src/c_modules/fine_movement/libimagedeform/include/image_grid.h
src/c_modules/fine_movement/libimagedeform/include/interpolation.h
src/c_modules/fine_movement/libimagedeform/src/image_deform.c
src/c_modules/fine_movement/libimagedeform/src/image_deform_gc.c
src/c_modules/fine_movement/libimagedeform/src/image_deform_lc.c
src/c_modules/fine_movement/libimagedeform/src/image_grid.c
src/c_modules/fine_movement/libimagedeform/src/interpolation.c
src/c_modules/fine_movement/libimagedeform/tests/deform_test.cc
src/c_modules/fine_movement/libimagedeform/tests/deform_test_gc.cc
src/c_modules/fine_movement/module/imagedeform.c
src/c_modules/fine_movement/module/imagedeform.h
src/c_modules/fine_movement/module/imagedeform_gc.c
src/c_modules/fine_movement/module/imagedeform_gc.h
src/c_modules/fine_movement/module/imagedeform_lc.c
src/c_modules/fine_movement/module/imagedeform_lc.h
src/c_modules/fine_movement/module/imagedeform_module.c
src/c_modules/fine_movement/module/imagegrid.c
src/c_modules/fine_movement/module/imagegrid.h
src/c_modules/movements/module.c
src/c_modules/movements/lib/flat.c
src/c_modules/movements/lib/flat.h
src/c_modules/movements/lib/sphere.c
vstarstack.egg-info/PKG-INFO
vstarstack.egg-info/SOURCES.txt
vstarstack.egg-info/dependency_links.txt
vstarstack.egg-info/entry_points.txt
vstarstack.egg-info/requires.txt
vstarstack.egg-info/top_level.txt