Metadata-Version: 2.1
Name: vstarstack
Version: 0.3.3
Summary: Stacking astrophotos
Author: Vladislav Tsendrovskii
Requires: setuptools
Requires: cython
Requires: numpy
License-File: LICENSE.txt
Requires-Dist: numpy
Requires-Dist: astropy
Requires-Dist: rawpy<=0.21.0
Requires-Dist: pillow
Requires-Dist: imageio
Requires-Dist: exifread
Requires-Dist: opencv-python
Requires-Dist: scikit-image
Requires-Dist: scipy>=1.11.0
Requires-Dist: imutils
Requires-Dist: matplotlib
Requires-Dist: pytz
Requires-Dist: psutil
